ape_ens/__init__.py
ape_ens/converter.py
ape_ens/py.typed
ape_ens/version.py
ape_ens/utils/__init__.py
ape_ens/utils/namehash.py
ape_ens-0.8.0.dist-info/LICENSE
ape_ens-0.8.0.dist-info/METADATA
ape_ens-0.8.0.dist-info/WHEEL
ape_ens-0.8.0.dist-info/top_level.txt
ape_ens-0.8.0.dist-info/RECORD
